voyage_touch/__init__.py
voyage_touch/assc/__init__.py
voyage_touch/assc/assc.py
voyage_touch/assc/evaluate.py
voyage_touch/assc/markovian.py
voyage_touch/assc/model.py
voyage_touch/assc/timeseries.py
voyage_touch/assc/data/__init__.py
voyage_touch/assc/data/load.py
voyage_touch/assc/data/markovian.py
voyage_touch/assc/data/store.py
voyage_touch/assc/policies/__init__.py
voyage_touch/assc/policies/fsr_heuristic.py
voyage_touch/sensor/__init__.py
voyage_touch/sensor/sensor.py
voyage_touch/sensor/sensor_reader.py
voyage_touch/sensor/sensor_type.py
voyage_touch-0.0.3.dist-info/LICENSE
voyage_touch-0.0.3.dist-info/METADATA
voyage_touch-0.0.3.dist-info/WHEEL
voyage_touch-0.0.3.dist-info/top_level.txt
voyage_touch-0.0.3.dist-info/RECORD
