Metadata-Version: 2.1
Name: voyage-touch
Version: 0.0.3
Summary: Open-source low-cost robot touch sensor hardware and controls.
Author: Ville Kuosmanen
Project-URL: Homepage, https://github.com/villekuosmanen/voyage-touch
Project-URL: Issues, https://github.com/villekuosmanen/voyage-touch/issues
Classifier: Programming Language :: Python :: 3
Classifier: License :: OSI Approved :: MIT License
Classifier: Operating System :: OS Independent
Requires-Python: >=3.6
License-File: LICENSE
Requires-Dist: numpy >=1.16
Requires-Dist: pyserial >=3.0
Requires-Dist: scikit-learn
